qubit_opencensus-0.1.16-py3.5-nspkg.pth
qubit/opencensus/__init__.py
qubit/opencensus/trace/__init__.py
qubit/opencensus/trace/asyncio_context.py
qubit/opencensus/trace/exporters/__init__.py
qubit/opencensus/trace/exporters/jaeger_exporter.py
qubit/opencensus/trace/ext/__init__.py
qubit/opencensus/trace/ext/aiohttp/__init__.py
qubit/opencensus/trace/ext/aiohttp/trace.py
qubit/opencensus/trace/ext/aioredis/__init__.py
qubit/opencensus/trace/ext/aioredis/trace.py
qubit/opencensus/trace/ext/sanic/__init__.py
qubit/opencensus/trace/ext/sanic/sanic_middleware.py
qubit/opencensus/trace/propagation/__init__.py
qubit/opencensus/trace/propagation/jaeger_format.py
qubit/opencensus/trace/samplers/__init__.py
qubit/opencensus/trace/samplers/probability.py
qubit/opencensus/trace/tracers/__init__.py
qubit/opencensus/trace/tracers/asyncio_context_tracer.py
qubit_opencensus-0.1.16.dist-info/METADATA
qubit_opencensus-0.1.16.dist-info/RECORD
qubit_opencensus-0.1.16.dist-info/WHEEL
qubit_opencensus-0.1.16.dist-info/namespace_packages.txt
qubit_opencensus-0.1.16.dist-info/top_level.txt
