Metadata-Version: 2.1
Name: qubit-opencensus
Version: 0.1.16
Summary: Various extensions for OpenCensus
Home-page: https://github.com/QubitProducts/opencensus-utils
Author: Qubit
Author-email: tristan@qubit.com
License: Apache-2.0
Platform: UNKNOWN
Classifier: Intended Audience :: Developers
Classifier: Development Status :: 3 - Alpha
Classifier: Intended Audience :: Developers
Classifier: License :: OSI Approved :: Apache Software License
Classifier: Programming Language :: Python
Classifier: Programming Language :: Python :: 3
Classifier: Programming Language :: Python :: 3.4
Classifier: Programming Language :: Python :: 3.5
Classifier: Programming Language :: Python :: 3.6
